dataknobs_llm/__init__.py
dataknobs_llm/exceptions.py
dataknobs_llm/py.typed
dataknobs_llm/template_utils.py
dataknobs_llm/testing.py
dataknobs_llm/conversations/__init__.py
dataknobs_llm/conversations/manager.py
dataknobs_llm/conversations/middleware.py
dataknobs_llm/conversations/storage.py
dataknobs_llm/conversations/flow/__init__.py
dataknobs_llm/conversations/flow/adapter.py
dataknobs_llm/conversations/flow/conditions.py
dataknobs_llm/conversations/flow/flow.py
dataknobs_llm/extraction/__init__.py
dataknobs_llm/extraction/observability.py
dataknobs_llm/extraction/schema_extractor.py
dataknobs_llm/fsm_integration/__init__.py
dataknobs_llm/fsm_integration/functions.py
dataknobs_llm/fsm_integration/resources.py
dataknobs_llm/fsm_integration/workflows.py
dataknobs_llm/llm/__init__.py
dataknobs_llm/llm/base.py
dataknobs_llm/llm/utils.py
dataknobs_llm/llm/providers/__init__.py
dataknobs_llm/llm/providers/anthropic.py
dataknobs_llm/llm/providers/base.py
dataknobs_llm/llm/providers/echo.py
dataknobs_llm/llm/providers/huggingface.py
dataknobs_llm/llm/providers/ollama.py
dataknobs_llm/llm/providers/openai.py
dataknobs_llm/prompts/__init__.py
dataknobs_llm/prompts/adapters/__init__.py
dataknobs_llm/prompts/adapters/dataknobs_backend_adapter.py
dataknobs_llm/prompts/adapters/dict_adapter.py
dataknobs_llm/prompts/adapters/inmemory_adapter.py
dataknobs_llm/prompts/adapters/resource_adapter.py
dataknobs_llm/prompts/base/__init__.py
dataknobs_llm/prompts/base/abstract_prompt_library.py
dataknobs_llm/prompts/base/base_prompt_library.py
dataknobs_llm/prompts/base/types.py
dataknobs_llm/prompts/builders/__init__.py
dataknobs_llm/prompts/builders/async_prompt_builder.py
dataknobs_llm/prompts/builders/base_prompt_builder.py
dataknobs_llm/prompts/builders/prompt_builder.py
dataknobs_llm/prompts/implementations/__init__.py
dataknobs_llm/prompts/implementations/composite_library.py
dataknobs_llm/prompts/implementations/config_library.py
dataknobs_llm-0.3.3.dist-info/METADATA
dataknobs_llm-0.3.3.dist-info/WHEEL
dataknobs_llm-0.3.3.dist-info/RECORD
