Metadata-Version: 2.4
Name: dataknobs-llm
Version: 0.3.3
Summary: LLM utilities for DataKnobs
Author-email: Spence Koehler <KoehlerSB747@gmail.com>
Requires-Python: >=3.10
Requires-Dist: dataknobs-common>=1.0.1
Requires-Dist: dataknobs-config>=0.2.0
Requires-Dist: dataknobs-data>=0.3.1
Requires-Dist: jinja2>=3.1.0
Requires-Dist: pyyaml>=6.0
Provides-Extra: all
Requires-Dist: aiohttp>=3.8.0; extra == 'all'
Requires-Dist: anthropic>=0.18.0; extra == 'all'
Requires-Dist: openai>=1.0.0; extra == 'all'
Requires-Dist: torch>=2.0.0; extra == 'all'
Requires-Dist: transformers>=4.30.0; extra == 'all'
Provides-Extra: anthropic
Requires-Dist: anthropic>=0.18.0; extra == 'anthropic'
Provides-Extra: embeddings
Requires-Dist: torch>=2.0.0; extra == 'embeddings'
Requires-Dist: transformers>=4.30.0; extra == 'embeddings'
Provides-Extra: huggingface
Requires-Dist: aiohttp>=3.8.0; extra == 'huggingface'
Provides-Extra: ollama
Requires-Dist: aiohttp>=3.8.0; extra == 'ollama'
Provides-Extra: openai
Requires-Dist: openai>=1.0.0; extra == 'openai'
